fact/__init__.py
fact/catalog_parser/__init__.py
fact/catalog_parser/config.py
fact/catalog_parser/data_downloader.py
fact/catalog_parser/gaia_qso_parser.py
fact/catalog_parser/icrf_parser.py
fact/catalog_utils/__init__.py
fact/catalog_utils/analysis_tools.py
fact/catalog_utils/catalog_operations.py
fact/catalog_utils/coordinate_system.py
fact/catalog_utils/data_cleaning.py
fact/catalog_utils/error_ellipse.py
fact/catalog_utils/galactic_aberration.py
fact/catalog_utils/iers_transformations.py
fact/catalog_utils/visualizations.py
fact/catalog_utils/vsh_analysis.py
fact/catalog_utils/vsh_utils.py
fact/catalog_utils/tests/__init__.py
fact/catalog_utils/tests/test_vsh_analysis.py
fact4astro-2024.8.26.dist-info/LICENSE
fact4astro-2024.8.26.dist-info/METADATA
fact4astro-2024.8.26.dist-info/WHEEL
fact4astro-2024.8.26.dist-info/top_level.txt
fact4astro-2024.8.26.dist-info/RECORD
