Metadata-Version: 2.1
Name: fact4astro
Version: 2024.8.26
Summary: A python package for astrometric catalog analyses
Author-email: Niu Liu <niu.liu@nju.edu.cn>
Maintainer-email: Niu Liu <niu.liu@nju.edu.cn>
Project-URL: Homepage, https://pypi.org/project/fact4astro/
Project-URL: Repository, https://git.nju.edu.cn/neo/fact.git
Project-URL: Changelog, https://git.nju.edu.cn/neo/fact/-/blob/main/CHANGELOG
Keywords: astrometry,catalog,vlbi,gaia
Classifier: Development Status :: 4 - Beta
Classifier: License :: OSI Approved :: MIT License
Classifier: Intended Audience :: Developers
Classifier: Topic :: Software Development :: Build Tools
Classifier: License :: OSI Approved :: MIT License
Classifier: Programming Language :: Python :: 3.12
Requires-Python: >=3.0
License-File: LICENSE
Requires-Dist: urllib3
Requires-Dist: astropy
Requires-Dist: numpy
Requires-Dist: scipy
Requires-Dist: astroquery
Requires-Dist: pyyaml >=5.4
Requires-Dist: matplotlib
